.dockerignore
Dockerfile
LICENSE
MANIFEST.in
README.md
requirements.txt
requirements_dev.txt
requirements_testing.txt
setup.cfg
setup.json
setup.py
.docker/run.sh
aiida_optimade/__init__.py
aiida_optimade/config.json
aiida_optimade/config.py
aiida_optimade/entry_collections.py
aiida_optimade/main.py
aiida_optimade/middleware.py
aiida_optimade/utils.py
aiida_optimade.egg-info/PKG-INFO
aiida_optimade.egg-info/SOURCES.txt
aiida_optimade.egg-info/dependency_links.txt
aiida_optimade.egg-info/entry_points.txt
aiida_optimade.egg-info/requires.txt
aiida_optimade.egg-info/top_level.txt
aiida_optimade/cli/__init__.py
aiida_optimade/cli/cmd_aiida_optimade.py
aiida_optimade/cli/cmd_calc.py
aiida_optimade/cli/cmd_init.py
aiida_optimade/cli/cmd_run.py
aiida_optimade/cli/options.py
aiida_optimade/cli/utils.py
aiida_optimade/common/__init__.py
aiida_optimade/common/exceptions.py
aiida_optimade/common/logger.py
aiida_optimade/common/warnings.py
aiida_optimade/data/links.json
aiida_optimade/mappers/__init__.py
aiida_optimade/mappers/entries.py
aiida_optimade/mappers/structures.py
aiida_optimade/models/__init__.py
aiida_optimade/models/structures.py
aiida_optimade/routers/__init__.py
aiida_optimade/routers/info.py
aiida_optimade/routers/links.py
aiida_optimade/routers/structures.py
aiida_optimade/routers/utils.py
aiida_optimade/transformers/__init__.py
aiida_optimade/transformers/aiida.py
aiida_optimade/translators/__init__.py
aiida_optimade/translators/cifs.py
aiida_optimade/translators/entities.py
aiida_optimade/translators/structures.py
aiida_optimade/translators/utils.py
profiles/config.j2
profiles/docker-compose-mongo.j2
profiles/docker-compose-mongo.yml
profiles/docker-compose.j2
profiles/docker-compose.yml
profiles/test_psql_dos.json