Metadata-Version: 2.1
Name: aiida-optimade
Version: 1.1.1
Summary: Expose an AiiDA database according to the [OPTIMADE API specification](https://www.optimade.org).
Home-page: https://github.com/aiidateam/aiida-optimade
Author: Casper Welzel Andersen
Author-email: developers@aiida.net
License: MIT License
Keywords: optimade aiida materials
Classifier: Development Status :: 4 - Beta
Classifier: Framework :: AiiDA
Classifier: Intended Audience :: Science/Research
Classifier: License :: OSI Approved :: MIT License
Classifier: Operating System :: MacOS :: MacOS X
Classifier: Operating System :: POSIX :: Linux
Classifier: Programming Language :: Python :: 3 :: Only
Classifier: Programming Language :: Python :: 3.8
Classifier: Programming Language :: Python :: 3.9
Classifier: Programming Language :: Python :: 3.10
Classifier: Intended Audience :: Developers
Classifier: Topic :: Database
Classifier: Topic :: Database :: Database Engines/Servers
Classifier: Topic :: Database :: Front-Ends
Classifier: Topic :: Internet :: WWW/HTTP :: WSGI
Classifier: Topic :: Internet :: WWW/HTTP :: WSGI :: Server
Classifier: Topic :: Scientific/Engineering
Classifier: Topic :: Scientific/Engineering :: Chemistry
Classifier: Topic :: Scientific/Engineering :: Physics
Requires-Python: >=3.8
Provides-Extra: dev
Provides-Extra: testing
License-File: LICENSE
